{ "qualification": {"rou_code":"PCNRS1ENNTL1","rou_name":"Neonatal","prg_code":"PCNRS","prg_snam":"PGCERTNURS","prg_name":"PGCert Nursing"},"diets": [{"pdt_code":"PCNRS1ENNTL116","pdt_type":"P","minCred":"60","diet_Name":"Neonatal courses - 60 credits"}],"dietGroups": [{"pdm_pdtc":"PCNRS1ENNTL116","pdm_seqn":"005","pdm_data":"CRD","pdm_fmcc":"PDMPCNRS1ENNTL17C16","pdm_minv":60.00,"pdm_maxv":60.00,"pdm_oper":"AND","pdm_fmcn":"","fmc_name":"Neonatal 700-level course list"}],"groupCourses": [{"pdm_fmcc":"PDMPCNRS1ENNTL17C16","fme_seq":"001","fme_modp":"168725","lev_code":"700","mtc_code":"OBS"},{"pdm_fmcc":"PDMPCNRS1ENNTL17C16","fme_seq":"002","fme_modp":"168729","lev_code":"700","mtc_code":"OBS"}] }