{ "qualification": {"rou_code":"PDART1EPHLS1","rou_name":"Philosophy","prg_code":"PDART","prg_snam":"PGDIPARTS","prg_name":"PGDip Arts"},"diets": [{"pdt_code":"PDART1EPHLS116","pdt_type":"P","minCred":"120","diet_Name":"Philosophy courses - 120 credits"}],"dietGroups": [{"pdm_pdtc":"PDART1EPHLS116","pdm_seqn":"005","pdm_data":"CRD","pdm_fmcc":"PDMPDART1EPHLS17C16","pdm_minv":30.00,"pdm_maxv":30.00,"pdm_oper":"AND","pdm_fmcn":"","fmc_name":"Philosophy 700-level course list"},{"pdm_pdtc":"PDART1EPHLS116","pdm_seqn":"705","pdm_data":"CRD","pdm_fmcc":"PDMPDART1EPHLS17R116","pdm_minv":90.00,"pdm_maxv":90.00,"pdm_oper":"AND","pdm_fmcn":"","fmc_name":"Philosophy 700-level course list"}],"groupCourses": [{"pdm_fmcc":"PDMPDART1EPHLS17C16","fme_seq":"001","fme_modp":"134710","lev_code":"700"},{"pdm_fmcc":"PDMPDART1EPHLS17R116","fme_seq":"001","fme_modp":"134740","lev_code":"700"},{"pdm_fmcc":"PDMPDART1EPHLS17R116","fme_seq":"002","fme_modp":"134750","lev_code":"700"},{"pdm_fmcc":"PDMPDART1EPHLS17R116","fme_seq":"003","fme_modp":"134760","lev_code":"700"},{"pdm_fmcc":"PDMPDART1EPHLS17R116","fme_seq":"004","fme_modp":"134798","lev_code":"700"},{"pdm_fmcc":"PDMPDART1EPHLS17R116","fme_seq":"005","fme_modp":"134799","lev_code":"700"}] }