{ "qualification": {"rou_code":"PDHLS1EMDLS1","rou_name":"Medical Laboratory Science","prg_code":"PDHLS","prg_snam":"PGDIPHLTHSC","prg_name":"PGDip Health Science"},"diets": [{"pdt_code":"PDHLS1EMDLS119","pdt_type":"P","minCred":"120","diet_Name":"Medical Laboratory Science courses - 120 credits"}],"dietGroups": [{"pdm_pdtc":"PDHLS1EMDLS119","pdm_seqn":"005","pdm_data":"CRD","pdm_fmcc":"PDMPDHLS1EMDLS17C119","pdm_minv":120.00,"pdm_maxv":120.00,"pdm_oper":"AND","pdm_fmcn":"","fmc_name":"Medical Laboratory Science 700-level course list"}],"groupCourses": [{"pdm_fmcc":"PDMPDHLS1EMDLS17C119","fme_seq":"001","fme_modp":"168713","lev_code":"700"},{"pdm_fmcc":"PDMPDHLS1EMDLS17C119","fme_seq":"002","fme_modp":"202701","lev_code":"700"},{"pdm_fmcc":"PDMPDHLS1EMDLS17C119","fme_seq":"003","fme_modp":"202702","lev_code":"700"},{"pdm_fmcc":"PDMPDHLS1EMDLS17C119","fme_seq":"004","fme_modp":"202703","lev_code":"700"},{"pdm_fmcc":"PDMPDHLS1EMDLS17C119","fme_seq":"005","fme_modp":"202704","lev_code":"700"},{"pdm_fmcc":"PDMPDHLS1EMDLS17C119","fme_seq":"006","fme_modp":"202705","lev_code":"700"}] }