{ "qualification": {"rou_code":"PDPBH1XNOSP1","rou_name":"No Specialisation","prg_code":"PDPBH","prg_snam":"PGDIPPH","prg_name":"PGDip Public Health"},"diets": [{"pdt_code":"PDPBH1XNOSP116","pdt_type":"P","minCred":"120","diet_Name":"Postgraduate Diploma in Public Health courses - 120 credits"}],"dietGroups": [{"pdm_pdtc":"PDPBH1XNOSP116","pdm_seqn":"005","pdm_data":"CRD","pdm_fmcc":"PDMPDPBH1XNOSP17C122","pdm_minv":120.00,"pdm_maxv":120.00,"pdm_oper":"AND","pdm_fmcn":"","fmc_name":"700-level course list"}],"groupCourses": [{"pdm_fmcc":"PDMPDPBH1XNOSP17C122","fme_seq":"001","fme_modp":"231725","lev_code":"700"},{"pdm_fmcc":"PDMPDPBH1XNOSP17C122","fme_seq":"002","fme_modp":"231726","lev_code":"700"},{"pdm_fmcc":"PDMPDPBH1XNOSP17C122","fme_seq":"003","fme_modp":"231728","lev_code":"700"},{"pdm_fmcc":"PDMPDPBH1XNOSP17C122","fme_seq":"004","fme_modp":"231729","lev_code":"700"},{"pdm_fmcc":"PDMPDPBH1XNOSP17C122","fme_seq":"005","fme_modp":"231727","lev_code":"700"},{"pdm_fmcc":"PDMPDPBH1XNOSP17C122","fme_seq":"006","fme_modp":"231704","lev_code":"700"}] }