{ "qualification": {"rou_code":"PMFNN1XNOSP1","rou_name":"No Specialisation","prg_code":"PMFNN","prg_snam":"MFIN","prg_name":"Master Finance"},"diets": [{"pdt_code":"PMFNN1XNOSP116","pdt_type":"P","minCred":"180","diet_Name":"Master of Finance courses - 180 credits"}],"dietGroups": [{"pdm_pdtc":"PMFNN1XNOSP116","pdm_seqn":"005","pdm_data":"CRD","pdm_fmcc":"PDMPMFNN1XNOSP17C116","pdm_minv":30.00,"pdm_maxv":30.00,"pdm_oper":"AND","pdm_fmcn":"","fmc_name":"700-level course list"},{"pdm_pdtc":"PMFNN1XNOSP116","pdm_seqn":"705","pdm_data":"CRD","pdm_fmcc":"PDMPMFNN1XNOSP17R121","pdm_minv":90.00,"pdm_maxv":90.00,"pdm_oper":"AND","pdm_fmcn":"","fmc_name":"700-level course list"},{"pdm_pdtc":"PMFNN1XNOSP116","pdm_seqn":"805","pdm_data":"CRD","pdm_fmcc":"PDMPMFNN1XNOSP18R116","pdm_minv":60.00,"pdm_maxv":60.00,"pdm_oper":"AND","pdm_fmcn":"","fmc_name":"800-level course list"}],"groupCourses": [{"pdm_fmcc":"PDMPMFNN1XNOSP17C116","fme_seq":"001","fme_modp":"125785","lev_code":"700"},{"pdm_fmcc":"PDMPMFNN1XNOSP17R121","fme_seq":"001","fme_modp":"125732","lev_code":"700"},{"pdm_fmcc":"PDMPMFNN1XNOSP17R121","fme_seq":"002","fme_modp":"125740","lev_code":"700"},{"pdm_fmcc":"PDMPMFNN1XNOSP17R121","fme_seq":"003","fme_modp":"125781","lev_code":"700"},{"pdm_fmcc":"PDMPMFNN1XNOSP17R121","fme_seq":"004","fme_modp":"125700","lev_code":"700"},{"pdm_fmcc":"PDMPMFNN1XNOSP18R116","fme_seq":"001","fme_modp":"125850","lev_code":"800"},{"pdm_fmcc":"PDMPMFNN1XNOSP18R116","fme_seq":"002","fme_modp":"125851","lev_code":"800"},{"pdm_fmcc":"PDMPMFNN1XNOSP18R116","fme_seq":"003","fme_modp":"125892","lev_code":"800"}] }